ventaapi/__init__.py
ventaapi/api.py
ventaapi/humidifier.py
ventaapi/light.py
ventaapi/session.py
ventaapi-1.0.0.dist-info/METADATA
ventaapi-1.0.0.dist-info/WHEEL
ventaapi-1.0.0.dist-info/top_level.txt
ventaapi-1.0.0.dist-info/RECORD
