Metadata-Version: 2.1
Name: ventaapi
Version: 1.0.0
Summary: Local API connector library for Venta Air Washers
Home-page: UNKNOWN
Author: Vladislav Sharapov
License: MIT
Platform: UNKNOWN
Requires-Dist: aiohttp
Requires-Dist: asyncio
